graphs/__init__.py
graphs/floyd_warshall_bidirectional.py
my_graph_algorithms-0.1.2.dist-info/METADATA
my_graph_algorithms-0.1.2.dist-info/WHEEL
my_graph_algorithms-0.1.2.dist-info/top_level.txt
my_graph_algorithms-0.1.2.dist-info/RECORD
