Metadata-Version: 2.1
Name: my_graph_algorithms
Version: 0.1.2
Summary: A package for graph algorithms, including Floyd-Warshall.
Author: Hemanth Reddy Gangula
Author-email: hemanthreddy8181@gmail.com
Classifier: Programming Language :: Python :: 3
Classifier: License :: OSI Approved :: MIT License
Classifier: Operating System :: OS Independent
Requires-Python: >=3.6
